{
    "$schema": "http://json-schema.org/draft-07/schema",
    "$id": "https://raw.githubusercontent.com/mobie/mobie.github.io/master/schema/views.schema.json",
    "title": "MoBIEViewsSchema",
    "description": "Additional MoBIE viewss",
    "properties": {
        "views": {
            "description": "",
            "type": "object",
            "additionalProperties": {"$ref": "https://raw.githubusercontent.com/mobie/mobie.github.io/master/schema/view.schema.json"}
        }
    },
    "required": ["views"],
    "additionalProperties": false
}
